agentk.py
agentk-0.3.2.dist-info/LICENSE
agentk-0.3.2.dist-info/METADATA
agentk-0.3.2.dist-info/WHEEL
agentk-0.3.2.dist-info/entry_points.txt
agentk-0.3.2.dist-info/RECORD
