Metadata-Version: 2.3
Name: agentk
Version: 0.3.2
Summary: "AGENT" K is a complete minimalistic kubectl "doner"-wrap
License: MIT
Keywords: kubectl,tool,kubernetes
Author: Yauhen Yakimovich
Author-email: eugeny.yakimovitch@gmail.com
Requires-Python: >=3.6,<4.0
Classifier: License :: OSI Approved :: MIT License
Classifier: Programming Language :: Python :: 3
Classifier: Programming Language :: Python :: 3.6
Classifier: Programming Language :: Python :: 3.7
Classifier: Programming Language :: Python :: 3.8
Classifier: Programming Language :: Python :: 3.9
Classifier: Programming Language :: Python :: 3.10
Classifier: Programming Language :: Python :: 3.11
Classifier: Programming Language :: Python :: 3.12
Classifier: Programming Language :: Python :: 3.13
Requires-Dist: PyYAML (>=5.1.2)
Requires-Dist: clint (>=0.5.1)
Requires-Dist: pbs (==0.110) ; platform_system == "Windows"
Requires-Dist: pick (>=0.6.4)
Requires-Dist: sh (>=1.12.13)
Requires-Dist: windows-curses (>=2.0) ; platform_system == "Windows"
Project-URL: Homepage, https://gitlab.com/kubic-ci/k
Project-URL: Repository, https://gitlab.com/kubic-ci/k
